setup.py
VMAgent/VMAgent.py
VMAgent/__init__.py
VMAgent/collector.py
VMAgent/config.py
VMAgent/heartbeat.py
VMAgent/mongo.py
VMAgent/trigger_analysis.py
VMAgent.egg-info/PKG-INFO
VMAgent.egg-info/SOURCES.txt
VMAgent.egg-info/dependency_links.txt
VMAgent.egg-info/not-zip-safe
VMAgent.egg-info/requires.txt
VMAgent.egg-info/top_level.txt
bin/VMAgent
bin/VMAgent-stop