Metadata-Version: 1.0
Name: VMAgent
Version: 0.1.6
Summary: Openstack instance monitor agent
Home-page: http://github.com/zouyapeng/instance_monitor_agent
Author: Zouyapeng
Author-email: zyp19901009@163.com
License: Apache
Keywords: VMAgent OpenStack Instance Monitor
Platform: UNKNOWN
